{
  "schema_version": "1.0.0",
  "generated": "2026-07-14T17:52:47.546517",
  "policy": "Never guess units. Record Unknown when the dataset does not explicitly specify them. Do not assume millimeters or degrees.",
  "probe": {
    "explicit_units_found": false,
    "candidate_paths": []
  },
  "note": "Units are Unknown for every variable category because the dataset structure does not specify them.",
  "reason": "The MATLAB .mat hierarchy contains no fields documenting physical units for markers, angles, joint centers, COM, or clinical metrics. A structural probe for field names containing \"unit\" returned no matches. Therefore units are recorded as Unknown rather than assumed.",
  "recommendation": "MotionDatabase parser must leave units as Unknown unless an authoritative external specification is supplied separately. Do not hardcode millimeters or degrees.",
  "categories": {
    "markers": {
      "description": "3D marker trajectories",
      "unit_status": "Unknown",
      "unit_value": null,
      "source": null,
      "reason": "The MATLAB .mat hierarchy contains no fields documenting physical units for markers, angles, joint centers, COM, or clinical metrics. A structural probe for field names containing \"unit\" returned no matches. Therefore units are recorded as Unknown rather than assumed.",
      "variables": [
        "C7",
        "CLAV",
        "LANK",
        "LASI",
        "LBHD",
        "LELB",
        "LFHD",
        "LFIN",
        "LFRM",
        "LHEE",
        "LKNE",
        "LPSI",
        "LSHO",
        "LTHI",
        "LTOE",
        "LUPA",
        "LWRA",
        "LWRB",
        "RANK",
        "RASI",
        "RBAK",
        "RBHD",
        "RELB",
        "RFHD",
        "RFIN",
        "RFRM",
        "RHEE",
        "RKNE",
        "RPSI",
        "RSHO",
        "RTHI",
        "RTOE",
        "RUPA",
        "RWRA",
        "RWRB",
        "STRN",
        "T10"
      ]
    },
    "joint_angles": {
      "description": "Joint angle time series",
      "unit_status": "Unknown",
      "unit_value": null,
      "source": null,
      "reason": "The MATLAB .mat hierarchy contains no fields documenting physical units for markers, angles, joint centers, COM, or clinical metrics. A structural probe for field names containing \"unit\" returned no matches. Therefore units are recorded as Unknown rather than assumed.",
      "variables": [
        "LAbsAnkleAngle",
        "LAnkleAngles",
        "LElbowAngles",
        "LFootProgressAngles",
        "LHeadAngles",
        "LHipAngles",
        "LKneeAngles",
        "LNeckAngles",
        "LPelvisAngles",
        "LShoulderAngles",
        "LSpineAngles",
        "LThoraxAngles",
        "LWristAngles",
        "RAbsAnkleAngle",
        "RAnkleAngles",
        "RElbowAngles",
        "RFootProgressAngles",
        "RHeadAngles",
        "RHipAngles",
        "RKneeAngles",
        "RNeckAngles",
        "RPelvisAngles",
        "RShoulderAngles",
        "RSpineAngles",
        "RThoraxAngles",
        "RWristAngles"
      ]
    },
    "joint_centers": {
      "description": "Joint center positions",
      "unit_status": "Unknown",
      "unit_value": null,
      "source": null,
      "reason": "The MATLAB .mat hierarchy contains no fields documenting physical units for markers, angles, joint centers, COM, or clinical metrics. A structural probe for field names containing \"unit\" returned no matches. Therefore units are recorded as Unknown rather than assumed.",
      "variables": [
        "LAJC",
        "LHJC",
        "LKJC",
        "RAJC",
        "RHJC",
        "RKJC"
      ]
    },
    "center_of_mass": {
      "description": "Whole-body center of mass",
      "unit_status": "Unknown",
      "unit_value": null,
      "source": null,
      "reason": "The MATLAB .mat hierarchy contains no fields documenting physical units for markers, angles, joint centers, COM, or clinical metrics. A structural probe for field names containing \"unit\" returned no matches. Therefore units are recorded as Unknown rather than assumed.",
      "variables": [
        "CentreOfMass",
        "CentreOfMassFloor"
      ]
    },
    "segment_com": {
      "description": "Segment center of mass",
      "unit_status": "Unknown",
      "unit_value": null,
      "source": null,
      "reason": "The MATLAB .mat hierarchy contains no fields documenting physical units for markers, angles, joint centers, COM, or clinical metrics. A structural probe for field names containing \"unit\" returned no matches. Therefore units are recorded as Unknown rather than assumed.",
      "variables": [
        "HeadCOM",
        "LeftFemurCOM",
        "LeftFootCOM",
        "LeftHandCOM",
        "LeftHumerusCOM",
        "LeftRadiusCOM",
        "LeftTibiaCOM",
        "PelvisCOM",
        "RightFemurCOM",
        "RightFootCOM",
        "RightHandCOM",
        "RightHumerusCOM",
        "RightRadiusCOM",
        "RightTibiaCOM",
        "ThoraxCOM"
      ]
    },
    "clinical_metric": {
      "description": "Clinical outcome measures",
      "unit_status": "Unknown",
      "unit_value": null,
      "source": null,
      "reason": "The MATLAB .mat hierarchy contains no fields documenting physical units for markers, angles, joint centers, COM, or clinical metrics. A structural probe for field names containing \"unit\" returned no matches. Therefore units are recorded as Unknown rather than assumed.",
      "variables": [
        "FCKneeAtt",
        "MSKneeAtt",
        "MTC",
        "MxStKneeAtt",
        "NeckAng",
        "StpLen",
        "StpWth",
        "Upright",
        "WkVel",
        "nUpright"
      ]
    }
  }
}